.gitignore
LICENSE.txt
setup.py
motmot/__init__.py
motmot.wxvalidatedtext.egg-info/.gitignore
motmot.wxvalidatedtext.egg-info/PKG-INFO
motmot.wxvalidatedtext.egg-info/SOURCES.txt
motmot.wxvalidatedtext.egg-info/dependency_links.txt
motmot.wxvalidatedtext.egg-info/eager_resources.txt
motmot.wxvalidatedtext.egg-info/entry_points.txt
motmot.wxvalidatedtext.egg-info/namespace_packages.txt
motmot.wxvalidatedtext.egg-info/stdeb.cfg
motmot.wxvalidatedtext.egg-info/top_level.txt
motmot.wxvalidatedtext.egg-info/zip-safe
motmot/wxvalidatedtext/__init__.py
motmot/wxvalidatedtext/demo.py
motmot/wxvalidatedtext/demo.xrc
motmot/wxvalidatedtext/wxvalidatedtext.py