Metadata-Version: 1.0
Name: motmot.wxvalidatedtext
Version: 0.5.3
Summary: validated integer/float text entry field for wxPython
Home-page: http://code.astraw.com/projects/motmot
Author: Andrew Straw
Author-email: strawman@astraw.com
License: BSD
Platform: UNKNOWN
